Metadata-Version: 2.1
Name: abork-mailer
Version: 1.0.6
Summary: Mailer Library
Author: Alex Bork
License-File: LICENSE
